socks/__init__.py
socks/__main__.py
socks/classes.py
socks/constants.py
socks/exeptions.py
socks/functions.py
socks/generate_colored.py
socks/utils.py
socks_server-0.1.2.dist-info/WHEEL
socks_server-0.1.2.dist-info/METADATA
socks_server-0.1.2.dist-info/RECORD
