Metadata-Version: 2.1
Name: socks-server
Version: 0.1.2
Summary: Socks is a simple server framework, built only using the standard python library.
Home-page: https://github.com/PaddeCraft/socks
Author: PaddeCraft
Author-email: 70023807+PaddeCraft@users.noreply.github.com
Requires-Python: >=3.10,<4.0
Classifier: Programming Language :: Python :: 3
Classifier: Programming Language :: Python :: 3.10
Project-URL: Repository, https://github.com/PaddeCraft/socks
